[
  {
    "id": "6665",
    "name": "DUB",
    "size": "",
    "quality": "",
    "link_order": "-10",
    "movie_id": "135",
    "url": "https://gogoanime.film//koe-no-katachi-dub-episode-1",
    "type": "GogoAnime",
    "status": "1",
    "skip_available": "0",
    "intro_start": "",
    "intro_end": "0",
    "end_credits_marker": "0",
    "link_type": "0",
    "drm_uuid": "",
    "drm_license_uri": ""
  },
  {
    "id": "143",
    "name": "SERVER 1",
    "size": "",
    "quality": "",
    "link_order": "0",
    "movie_id": "135",
    "url": "https://movieshub.movieshubxd02.workers.dev/0:/Movieshubmirrorold/[Kayoanime]%20A%20Silent%20Voice%20(Koe%20no%20Katachi)%201080p%20Dual%20Audio%20HEVC/[Kayoanime]%20A%20Silent%20Voice%201080p%20Dual%20Audio%20HEVC.mkv",
    "type": "Mp4",
    "status": "1",
    "skip_available": "0",
    "intro_start": "00:00:00",
    "intro_end": "0",
    "end_credits_marker": "0",
    "link_type": "0",
    "drm_uuid": "",
    "drm_license_uri": ""
  },
  {
    "id": "6662",
    "name": "DUAL AUDIO",
    "size": "",
    "quality": "",
    "link_order": "0",
    "movie_id": "135",
    "url": "https://ahvsh.com/w/xi13bopvnu8n",
    "type": "Streamhide",
    "status": "1",
    "skip_available": "0",
    "intro_start": "",
    "intro_end": "0",
    "end_credits_marker": "0",
    "link_type": "0",
    "drm_uuid": "",
    "drm_license_uri": ""
  },
  {
    "id": "6664",
    "name": "DUAL AUDIO",
    "size": "",
    "quality": "",
    "link_order": "0",
    "movie_id": "135",
    "url": "https://embedwish.com/kez3isksgopx",
    "type": "Streamhide",
    "status": "1",
    "skip_available": "0",
    "intro_start": "",
    "intro_end": "0",
    "end_credits_marker": "0",
    "link_type": "0",
    "drm_uuid": "",
    "drm_license_uri": ""
  },
  {
    "id": "138",
    "name": "Server 01 | SUB",
    "size": "",
    "quality": "",
    "link_order": "1",
    "movie_id": "135",
    "url": "https://streamsb.net/e/1e512ilx8bvd.html",
    "type": "StreamSB",
    "status": "1",
    "skip_available": "0",
    "intro_start": "",
    "intro_end": "",
    "end_credits_marker": "0",
    "link_type": "0",
    "drm_uuid": null,
    "drm_license_uri": null
  },
  {
    "id": "139",
    "name": "Server 02 | DUB",
    "size": "",
    "quality": "",
    "link_order": "2",
    "movie_id": "135",
    "url": "https://watchsb.com/e/hyl6oh4icus5.html",
    "type": "StreamSB",
    "status": "1",
    "skip_available": "0",
    "intro_start": "",
    "intro_end": "",
    "end_credits_marker": "0",
    "link_type": "0",
    "drm_uuid": null,
    "drm_license_uri": null
  },
  {
    "id": "144",
    "name": "Server 03 | SUB",
    "size": "",
    "quality": "",
    "link_order": "3",
    "movie_id": "135",
    "url": "https://watchsb.com/e/f52fz33jubpi.html\t",
    "type": "StreamSB",
    "status": "1",
    "skip_available": "0",
    "intro_start": "",
    "intro_end": "",
    "end_credits_marker": "0",
    "link_type": "0",
    "drm_uuid": null,
    "drm_license_uri": null
  }
]