[
  {
    "id": "5612",
    "name": "SERVER 1 ",
    "size": "",
    "quality": "",
    "link_order": "0",
    "movie_id": "1588",
    "url": "https://movieshub.movieshub1.workers.dev/0:/Movieshubmirrornew/Passengers.2008.720p.BluRay.x264.%28English%20With%20Subtitles%29.Movieshubapk.online.org.mkv",
    "type": "Mp4",
    "status": "1",
    "skip_available": "0",
    "intro_start": "",
    "intro_end": "",
    "end_credits_marker": "0",
    "link_type": "0",
    "drm_uuid": "",
    "drm_license_uri": ""
  },
  {
    "id": "5613",
    "name": "SERVER 2",
    "size": "",
    "quality": "",
    "link_order": "0",
    "movie_id": "1588",
    "url": "https://streamsb.net/e/p96brbi9m35g.html",
    "type": "StreamSB",
    "status": "1",
    "skip_available": "0",
    "intro_start": "",
    "intro_end": "",
    "end_credits_marker": "0",
    "link_type": "0",
    "drm_uuid": "",
    "drm_license_uri": ""
  },
  {
    "id": "5616",
    "name": "SERVER 3",
    "size": "",
    "quality": "",
    "link_order": "0",
    "movie_id": "1588",
    "url": "https://cdn.cloudkp.com/watch/HE2DGMZQ",
    "type": "Mp4",
    "status": "1",
    "skip_available": "0",
    "intro_start": "",
    "intro_end": "",
    "end_credits_marker": "0",
    "link_type": "0",
    "drm_uuid": "",
    "drm_license_uri": ""
  }
]