[
  {
    "id": "5618",
    "name": "SERVER 1",
    "size": "",
    "quality": "",
    "link_order": "0",
    "movie_id": "1590",
    "url": "https://movieshub.movieshub1.workers.dev/0:/Movieshubmirrornew/Scream.1996.720P..Hindi.English.Esubs.Movieshubapk.online.org.mkv",
    "type": "Mp4",
    "status": "1",
    "skip_available": "0",
    "intro_start": "",
    "intro_end": "",
    "end_credits_marker": "0",
    "link_type": "0",
    "drm_uuid": "",
    "drm_license_uri": ""
  },
  {
    "id": "5619",
    "name": "SERVER 2",
    "size": "",
    "quality": "",
    "link_order": "0",
    "movie_id": "1590",
    "url": "https://streamsb.net/e/1es0abfgm27h.html",
    "type": "StreamSB",
    "status": "1",
    "skip_available": "0",
    "intro_start": "",
    "intro_end": "",
    "end_credits_marker": "0",
    "link_type": "0",
    "drm_uuid": "",
    "drm_license_uri": ""
  },
  {
    "id": "5620",
    "name": "SERVER 3",
    "size": "",
    "quality": "",
    "link_order": "0",
    "movie_id": "1590",
    "url": "https://cdn.cloudkp.com/watch/HE2DGNBQ",
    "type": "Mp4",
    "status": "1",
    "skip_available": "0",
    "intro_start": "",
    "intro_end": "",
    "end_credits_marker": "0",
    "link_type": "0",
    "drm_uuid": "",
    "drm_license_uri": ""
  }
]