[
  {
    "id": "7461",
    "name": "PREMIUM SERVER",
    "size": "",
    "quality": "",
    "link_order": "-1",
    "movie_id": "1979",
    "url": "http://89.40.6.249:8080/459/The_Boy_2016_720p_HEVC_BluRay_ORG_Dual_x265_AAC2_0_ESub_Movieshubapk.mkv?hash=AgADcg",
    "type": "Mp4",
    "status": "1",
    "skip_available": "0",
    "intro_start": "",
    "intro_end": "",
    "end_credits_marker": "0",
    "link_type": "1",
    "drm_uuid": "",
    "drm_license_uri": ""
  },
  {
    "id": "7456",
    "name": "SERVER 1",
    "size": "",
    "quality": "",
    "link_order": "0",
    "movie_id": "1979",
    "url": "https://movieshub.movieshub1.workers.dev/0:/Movieshubmirrornew/The.Boy.2016.720p.HEVC.BluRay.ORG.Dual.x265.AAC2.0.ESub%20%5BMovieshubapk.online%5D.mkv",
    "type": "Mp4",
    "status": "1",
    "skip_available": "0",
    "intro_start": "",
    "intro_end": "",
    "end_credits_marker": "0",
    "link_type": "0",
    "drm_uuid": "",
    "drm_license_uri": ""
  },
  {
    "id": "7457",
    "name": "SERVER 2",
    "size": "SB",
    "quality": "720P",
    "link_order": "0",
    "movie_id": "1979",
    "url": "https://streamsb.net/e/qc4gh31z7znq.html",
    "type": "StreamSB",
    "status": "1",
    "skip_available": "0",
    "intro_start": "",
    "intro_end": "",
    "end_credits_marker": "0",
    "link_type": "0",
    "drm_uuid": "",
    "drm_license_uri": ""
  },
  {
    "id": "7458",
    "name": "SERVER 3",
    "size": "SH",
    "quality": "720P",
    "link_order": "0",
    "movie_id": "1979",
    "url": "https://ahvsh.com/e/dw9na2mln4un",
    "type": "Embed",
    "status": "1",
    "skip_available": "0",
    "intro_start": "",
    "intro_end": "0",
    "end_credits_marker": "0",
    "link_type": "0",
    "drm_uuid": "",
    "drm_license_uri": ""
  },
  {
    "id": "7459",
    "name": "SERVER 4",
    "size": "SW",
    "quality": "720P",
    "link_order": "0",
    "movie_id": "1979",
    "url": "https://embedwish.com/di78je1b3jf4",
    "type": "Streamhide",
    "status": "1",
    "skip_available": "0",
    "intro_start": "",
    "intro_end": "0",
    "end_credits_marker": "0",
    "link_type": "0",
    "drm_uuid": "",
    "drm_license_uri": ""
  },
  {
    "id": "7460",
    "name": "SERVER 5",
    "size": "GLOBAL SERVER",
    "quality": "720P",
    "link_order": "0",
    "movie_id": "1979",
    "url": "https://embedwish.com/e/di78je1b3jf4",
    "type": "Embed",
    "status": "1",
    "skip_available": "0",
    "intro_start": "",
    "intro_end": "0",
    "end_credits_marker": "0",
    "link_type": "0",
    "drm_uuid": "",
    "drm_license_uri": ""
  }
]