[
  {
    "id": "8699",
    "name": "PREMIUM SERVER",
    "size": "",
    "quality": "",
    "link_order": "-1",
    "movie_id": "2114",
    "url": "http://89.40.6.249:8080/1866/Se7en_1995_720P_Bluray_Hindi_English_Esub_Movieshubapk_online_org.mkv?hash=AgADdA",
    "type": "Mp4",
    "status": "1",
    "skip_available": "0",
    "intro_start": "",
    "intro_end": "",
    "end_credits_marker": "0",
    "link_type": "1",
    "drm_uuid": "",
    "drm_license_uri": ""
  },
  {
    "id": "8700",
    "name": "AUTO SERVER",
    "size": "",
    "quality": "",
    "link_order": "0",
    "movie_id": "2114",
    "url": "https://embed.smashystream.com/playere.php?tmdb=807",
    "type": "Embed",
    "status": "1",
    "skip_available": "0",
    "intro_start": "",
    "intro_end": "",
    "end_credits_marker": "0",
    "link_type": "0",
    "drm_uuid": "",
    "drm_license_uri": ""
  },
  {
    "id": "8701",
    "name": "AUTO SERVER",
    "size": "",
    "quality": "",
    "link_order": "0",
    "movie_id": "2114",
    "url": "https://vidsrc.to/embed/movie/807",
    "type": "Embed",
    "status": "1",
    "skip_available": "0",
    "intro_start": "",
    "intro_end": "",
    "end_credits_marker": "0",
    "link_type": "0",
    "drm_uuid": "",
    "drm_license_uri": ""
  },
  {
    "id": "8702",
    "name": "AUTO SERVER",
    "size": "",
    "quality": "",
    "link_order": "0",
    "movie_id": "2114",
    "url": "https://autoembed.to/movie/tmdb/807",
    "type": "Embed",
    "status": "1",
    "skip_available": "0",
    "intro_start": "",
    "intro_end": "",
    "end_credits_marker": "0",
    "link_type": "0",
    "drm_uuid": "",
    "drm_license_uri": ""
  },
  {
    "id": "8703",
    "name": "AUTO SERVER",
    "size": "",
    "quality": "",
    "link_order": "0",
    "movie_id": "2114",
    "url": "https://www.nontongo.win/embed/movie/807",
    "type": "Embed",
    "status": "1",
    "skip_available": "0",
    "intro_start": "",
    "intro_end": "0",
    "end_credits_marker": "0",
    "link_type": "0",
    "drm_uuid": "",
    "drm_license_uri": ""
  },
  {
    "id": "8695",
    "name": "SERVER 1",
    "size": "",
    "quality": "",
    "link_order": "1",
    "movie_id": "2114",
    "url": "https://movieshub.movieshub1.workers.dev/0:/Movieshubmirrornew/Se7en.1995.720P.Bluray.Hindi.English.Esub.Movieshubapk.online.org.mkv",
    "type": "Mp4",
    "status": "1",
    "skip_available": "0",
    "intro_start": "",
    "intro_end": "",
    "end_credits_marker": "0",
    "link_type": "0",
    "drm_uuid": "",
    "drm_license_uri": ""
  },
  {
    "id": "8696",
    "name": "SERVER 2",
    "size": "",
    "quality": "MULTI QUALITY",
    "link_order": "2",
    "movie_id": "2114",
    "url": "https://oneupload.to/evzw5ido2iy3",
    "type": "Streamhide",
    "status": "1",
    "skip_available": "0",
    "intro_start": "",
    "intro_end": "",
    "end_credits_marker": "0",
    "link_type": "0",
    "drm_uuid": "",
    "drm_license_uri": ""
  },
  {
    "id": "8697",
    "name": "SERVER 3",
    "size": "",
    "quality": "",
    "link_order": "3",
    "movie_id": "2114",
    "url": "https://filemoon.in/e/d5iex0slymmy",
    "type": "Embed",
    "status": "1",
    "skip_available": "0",
    "intro_start": "",
    "intro_end": "",
    "end_credits_marker": "0",
    "link_type": "0",
    "drm_uuid": "",
    "drm_license_uri": ""
  },
  {
    "id": "8698",
    "name": "SERVER 4",
    "size": "",
    "quality": "",
    "link_order": "4",
    "movie_id": "2114",
    "url": "https://dropload.io/rxptbishskay",
    "type": "Streamhide",
    "status": "1",
    "skip_available": "0",
    "intro_start": "",
    "intro_end": "",
    "end_credits_marker": "0",
    "link_type": "0",
    "drm_uuid": "",
    "drm_license_uri": ""
  }
]