[
  {
    "id": "7825",
    "name": "AUTO SERVER",
    "size": "",
    "quality": "",
    "link_order": "-2",
    "movie_id": "270",
    "url": "https://autoembed.to/movie/tmdb/1726?server=1&ss=4",
    "type": "Embed",
    "status": "1",
    "skip_available": "0",
    "intro_start": "",
    "intro_end": "",
    "end_credits_marker": "0",
    "link_type": "0",
    "drm_uuid": "",
    "drm_license_uri": ""
  },
  {
    "id": "7824",
    "name": "SERVER 1",
    "size": "",
    "quality": "",
    "link_order": "-1",
    "movie_id": "270",
    "url": "http://89.40.6.249:8080/770/Iron_Man_2008_720p_10bit_BluRay_x265_HEVC_Org_Hindi_DDP_5_1_640Kbps.mkv?hash=AgADKQ",
    "type": "Mp4",
    "status": "1",
    "skip_available": "0",
    "intro_start": "",
    "intro_end": "",
    "end_credits_marker": "0",
    "link_type": "0",
    "drm_uuid": "",
    "drm_license_uri": ""
  },
  {
    "id": "1360",
    "name": "SERVER 2",
    "size": "",
    "quality": "720p",
    "link_order": "1",
    "movie_id": "270",
    "url": "https://movieshub.movieshubxd02.workers.dev/0:/Movieshubmirrorold/Iron%20Man%20(2008)%20720p%2010bit%20BluRay%20x265%20HEVC%20[Org%20Hindi%20DDP%205.1%20~%20640Kbps%20+%20English%20AAC%205.1]%20MSubs%20~%20GalaxyRG.mkv",
    "type": "Mkv",
    "status": "1",
    "skip_available": "0",
    "intro_start": "",
    "intro_end": "0",
    "end_credits_marker": "0",
    "link_type": "0",
    "drm_uuid": "",
    "drm_license_uri": ""
  },
  {
    "id": "1361",
    "name": "SERVER 2",
    "size": "",
    "quality": "720P",
    "link_order": "2",
    "movie_id": "270",
    "url": "https://dood.la/e/rb3nu9poflym",
    "type": "Embed",
    "status": "1",
    "skip_available": "0",
    "intro_start": "00:00:00",
    "intro_end": "0",
    "end_credits_marker": "0",
    "link_type": "0",
    "drm_uuid": "",
    "drm_license_uri": ""
  },
  {
    "id": "326",
    "name": "SERVER 3",
    "size": "",
    "quality": "",
    "link_order": "3",
    "movie_id": "270",
    "url": "https://streamsb.net/e/iu3roedzmvl3.html",
    "type": "StreamSB",
    "status": "1",
    "skip_available": "0",
    "intro_start": "",
    "intro_end": "0",
    "end_credits_marker": "0",
    "link_type": "0",
    "drm_uuid": "",
    "drm_license_uri": ""
  }
]