[
  {
    "id": "552",
    "name": "",
    "size": "",
    "quality": "",
    "link_order": "0",
    "movie_id": "483",
    "url": "https://streamsb.net/e/z1odnn6rhp4a.html",
    "type": "StreamSB",
    "status": "1",
    "skip_available": "0",
    "intro_start": "",
    "intro_end": "",
    "end_credits_marker": "0",
    "link_type": "0",
    "drm_uuid": null,
    "drm_license_uri": null
  },
  {
    "id": "1693",
    "name": "Server 2",
    "size": "",
    "quality": "",
    "link_order": "0",
    "movie_id": "483",
    "url": "https://dood.la/d/yfzdt88vpyk2",
    "type": "DoodStream",
    "status": "1",
    "skip_available": "0",
    "intro_start": "",
    "intro_end": "",
    "end_credits_marker": "0",
    "link_type": "0",
    "drm_uuid": null,
    "drm_license_uri": null
  },
  {
    "id": "1694",
    "name": "Server 1",
    "size": "",
    "quality": "",
    "link_order": "0",
    "movie_id": "483",
    "url": "https://movieshub.movieshubxd02.workers.dev/0:/Movieshubmirrorold/1337xHD.Shop-Firestarter_%282022%29_MLSB.Shop-Dual_Audio_Hindi_ORG_720p.mkv.mp4",
    "type": "Mkv",
    "status": "1",
    "skip_available": "0",
    "intro_start": "",
    "intro_end": "",
    "end_credits_marker": "0",
    "link_type": "0",
    "drm_uuid": null,
    "drm_license_uri": null
  }
]