[
  {
    "id": "8135",
    "name": "Premium Server",
    "size": "",
    "quality": "",
    "link_order": "-2",
    "movie_id": "54",
    "url": "https://movieshub.movieshubxd02.workers.dev/0:/Movieshubmirrorold/Jungle%20Cry%20(2022)%20Hindi%20720p%20WEBRip%20x264%20AAC%20ESub.mkv",
    "type": "Mp4",
    "status": "1",
    "skip_available": "0",
    "intro_start": "",
    "intro_end": "",
    "end_credits_marker": "0",
    "link_type": "1",
    "drm_uuid": "",
    "drm_license_uri": ""
  },
  {
    "id": "8136",
    "name": "Auto Server",
    "size": "",
    "quality": "",
    "link_order": "-1",
    "movie_id": "54",
    "url": "https://autoembed.to/movie/imdb/tt9319826",
    "type": "Embed",
    "status": "1",
    "skip_available": "0",
    "intro_start": "",
    "intro_end": "1",
    "end_credits_marker": "0",
    "link_type": "0",
    "drm_uuid": "",
    "drm_license_uri": ""
  },
  {
    "id": "1103",
    "name": "Server 1",
    "size": "",
    "quality": "",
    "link_order": "1",
    "movie_id": "54",
    "url": "http://89.40.6.249:8080/1086/Jungle+Cry+%282022%29+Hindi+720p+WEBRip+x264+AAC+ESub.mkv?hash=AgADkQ",
    "type": "Mp4",
    "status": "1",
    "skip_available": "0",
    "intro_start": "",
    "intro_end": "0",
    "end_credits_marker": "0",
    "link_type": "0",
    "drm_uuid": "",
    "drm_license_uri": ""
  },
  {
    "id": "1025",
    "name": "Server 2",
    "size": "",
    "quality": "SW",
    "link_order": "2",
    "movie_id": "54",
    "url": "https://embedwish.com/ej3vc9mcphnk",
    "type": "Streamhide",
    "status": "1",
    "skip_available": "0",
    "intro_start": "",
    "intro_end": "0",
    "end_credits_marker": "0",
    "link_type": "0",
    "drm_uuid": "",
    "drm_license_uri": ""
  },
  {
    "id": "55",
    "name": "Server 3",
    "size": "",
    "quality": "FM",
    "link_order": "3",
    "movie_id": "54",
    "url": "https://filemoon.in/e/zvccaxioic3z",
    "type": "Embed",
    "status": "1",
    "skip_available": "0",
    "intro_start": "",
    "intro_end": "0",
    "end_credits_marker": "0",
    "link_type": "0",
    "drm_uuid": "",
    "drm_license_uri": ""
  }
]