[
  {
    "id": "2471",
    "name": "720P",
    "size": "",
    "quality": "",
    "link_order": "0",
    "movie_id": "833",
    "url": "https://movieshub.movieshubxd02.workers.dev/0:/Movieshubmirrorold/BHMISKMHD%20%282017%29%20www.SkymoviesHD.Life%20720p%20HEVC%20HDRip%20Hindi%20x265%20ESUb.mkv",
    "type": "Mkv",
    "status": "1",
    "skip_available": "0",
    "intro_start": "",
    "intro_end": "",
    "end_credits_marker": "0",
    "link_type": "0",
    "drm_uuid": null,
    "drm_license_uri": null
  },
  {
    "id": "2472",
    "name": "SERVER HD",
    "size": "",
    "quality": "",
    "link_order": "0",
    "movie_id": "833",
    "url": "https://dood.la/d/qx1recv75mv5",
    "type": "DoodStream",
    "status": "1",
    "skip_available": "0",
    "intro_start": "",
    "intro_end": "",
    "end_credits_marker": "0",
    "link_type": "0",
    "drm_uuid": null,
    "drm_license_uri": null
  },
  {
    "id": "2473",
    "name": "SERVER HQ",
    "size": "",
    "quality": "",
    "link_order": "0",
    "movie_id": "833",
    "url": "https://streamsb.net/e/cvsvjkpy9o29.html",
    "type": "StreamSB",
    "status": "1",
    "skip_available": "0",
    "intro_start": "",
    "intro_end": "",
    "end_credits_marker": "0",
    "link_type": "0",
    "drm_uuid": null,
    "drm_license_uri": null
  }
]