[
  {
    "id": "440",
    "name": "",
    "size": "",
    "quality": "",
    "link_order": "0",
    "movie_id": "380",
    "url": "https://streamsb.net/e/itdxtylodfqn.html",
    "type": "StreamSB",
    "status": "1",
    "skip_available": "0",
    "intro_start": "",
    "intro_end": "",
    "end_credits_marker": "0",
    "link_type": "0",
    "drm_uuid": null,
    "drm_license_uri": null
  },
  {
    "id": "1453",
    "name": "Server 1",
    "size": "",
    "quality": "",
    "link_order": "0",
    "movie_id": "380",
    "url": "https://movieshub.movieshubxd02.workers.dev/0:/Movieshubmirrorold/1337xHD.Shop-Runway_34_%282022%29_MLSBD.Shop-Hindi_AMZN_720p.mkv.mp4",
    "type": "Mkv",
    "status": "1",
    "skip_available": "0",
    "intro_start": "",
    "intro_end": "",
    "end_credits_marker": "0",
    "link_type": "0",
    "drm_uuid": null,
    "drm_license_uri": null
  },
  {
    "id": "1454",
    "name": "Server 2",
    "size": "",
    "quality": "",
    "link_order": "0",
    "movie_id": "380",
    "url": "https://dood.la/d/8c5jf9srmzsf",
    "type": "DoodStream",
    "status": "1",
    "skip_available": "0",
    "intro_start": "",
    "intro_end": "",
    "end_credits_marker": "0",
    "link_type": "0",
    "drm_uuid": null,
    "drm_license_uri": null
  }
]