[
  {
    "id": "2602",
    "name": "480P",
    "size": "",
    "quality": "",
    "link_order": "0",
    "movie_id": "866",
    "url": "https://movieshub.movieshubxd02.workers.dev/0:/Movieshubmirrorold/Anthakshari%20%282022%29%20%7BHindiMalayalam%7D%20480p%20WEBDL%20ESub%20Plexmovies.xyz.mkv",
    "type": "Mkv",
    "status": "1",
    "skip_available": "0",
    "intro_start": "",
    "intro_end": "",
    "end_credits_marker": "0",
    "link_type": "0",
    "drm_uuid": null,
    "drm_license_uri": null
  },
  {
    "id": "2603",
    "name": "720P",
    "size": "",
    "quality": "",
    "link_order": "0",
    "movie_id": "866",
    "url": "https://movieshub.movieshubxd02.workers.dev/0:/Movieshubmirrorold/Anthakshari_%282022%29_%7BHindi-Malayalam%7D_720p_WEB-DL_ESub_Plexmovies.xyz.mkv",
    "type": "Mkv",
    "status": "1",
    "skip_available": "0",
    "intro_start": "",
    "intro_end": "",
    "end_credits_marker": "0",
    "link_type": "0",
    "drm_uuid": null,
    "drm_license_uri": null
  },
  {
    "id": "2604",
    "name": "SERVER HD",
    "size": "",
    "quality": "",
    "link_order": "0",
    "movie_id": "866",
    "url": "https://dood.la/d/gq71oqw39uwp",
    "type": "DoodStream",
    "status": "1",
    "skip_available": "0",
    "intro_start": "",
    "intro_end": "",
    "end_credits_marker": "0",
    "link_type": "0",
    "drm_uuid": null,
    "drm_license_uri": null
  },
  {
    "id": "2605",
    "name": "SERVER HQ",
    "size": "",
    "quality": "",
    "link_order": "0",
    "movie_id": "866",
    "url": "https://streamsb.net/e/uyty6gq0kk9t.html",
    "type": "StreamSB",
    "status": "1",
    "skip_available": "0",
    "intro_start": "",
    "intro_end": "",
    "end_credits_marker": "0",
    "link_type": "0",
    "drm_uuid": null,
    "drm_license_uri": null
  }
]