[
  {
    "id": "2712",
    "name": "Server 1",
    "size": "",
    "quality": "",
    "link_order": "0",
    "movie_id": "892",
    "url": "https://movieshub.movieshubxd02.workers.dev/0:/Movieshubmirrorold/Blade.Runner.2049.2019.480p.BRRip.Hindi.Dual-Audio.TheMoviesflix.cx.mkv",
    "type": "Mkv",
    "status": "1",
    "skip_available": "0",
    "intro_start": "",
    "intro_end": "",
    "end_credits_marker": "0",
    "link_type": "0",
    "drm_uuid": null,
    "drm_license_uri": null
  },
  {
    "id": "2713",
    "name": "Server 2",
    "size": "",
    "quality": "",
    "link_order": "0",
    "movie_id": "892",
    "url": "https://dood.la/d/rnqiwb4av41g",
    "type": "DoodStream",
    "status": "1",
    "skip_available": "0",
    "intro_start": "",
    "intro_end": "",
    "end_credits_marker": "0",
    "link_type": "0",
    "drm_uuid": null,
    "drm_license_uri": null
  },
  {
    "id": "2714",
    "name": "Server 3",
    "size": "",
    "quality": "",
    "link_order": "0",
    "movie_id": "892",
    "url": "https://streamsb.net/e/c3idtz4l9fmj.html",
    "type": "StreamSB",
    "status": "1",
    "skip_available": "0",
    "intro_start": "",
    "intro_end": "",
    "end_credits_marker": "0",
    "link_type": "0",
    "drm_uuid": null,
    "drm_license_uri": null
  }
]