[
  {
    "id": "8371",
    "name": "Premium Server",
    "size": "",
    "quality": "",
    "link_order": "-2",
    "movie_id": "97",
    "url": "https://movieshub.movieshubxd02.workers.dev/0:/Movieshubmirrorold/1QFvZOpyjV5doBpNOExjEgn_Sxsd779TO.mp4",
    "type": "Mp4",
    "status": "1",
    "skip_available": "0",
    "intro_start": "",
    "intro_end": "",
    "end_credits_marker": "0",
    "link_type": "1",
    "drm_uuid": "",
    "drm_license_uri": ""
  },
  {
    "id": "8373",
    "name": "Auto Server",
    "size": "",
    "quality": "",
    "link_order": "-1",
    "movie_id": "97",
    "url": "https://autoembed.to/movie/imdb/tt10838180",
    "type": "Embed",
    "status": "1",
    "skip_available": "0",
    "intro_start": "",
    "intro_end": "",
    "end_credits_marker": "0",
    "link_type": "0",
    "drm_uuid": "",
    "drm_license_uri": ""
  },
  {
    "id": "1122",
    "name": "Server `1",
    "size": "",
    "quality": "",
    "link_order": "1",
    "movie_id": "97",
    "url": "https://movieshub.movieshubxd02.workers.dev/0:/Movieshubmirrorold/1QFvZOpyjV5doBpNOExjEgn_Sxsd779TO.mp4",
    "type": "Mp4",
    "status": "1",
    "skip_available": "0",
    "intro_start": "00:00:00",
    "intro_end": "0",
    "end_credits_marker": "0",
    "link_type": "0",
    "drm_uuid": "",
    "drm_license_uri": ""
  },
  {
    "id": "8372",
    "name": "Server 2 ",
    "size": "",
    "quality": "",
    "link_order": "2",
    "movie_id": "97",
    "url": "http://89.40.6.249:8080/1286/1QFvZOpyjV5doBpNOExjEgn_Sxsd779TO.mp4?hash=AgADcg",
    "type": "Mp4",
    "status": "1",
    "skip_available": "0",
    "intro_start": "",
    "intro_end": "",
    "end_credits_marker": "0",
    "link_type": "0",
    "drm_uuid": "",
    "drm_license_uri": ""
  },
  {
    "id": "1036",
    "name": "Server 3",
    "size": "",
    "quality": "SW",
    "link_order": "3",
    "movie_id": "97",
    "url": "https://embedwish.com/4rizsona1bp9",
    "type": "Streamhide",
    "status": "1",
    "skip_available": "0",
    "intro_start": "00:00:00",
    "intro_end": "0",
    "end_credits_marker": "0",
    "link_type": "0",
    "drm_uuid": "",
    "drm_license_uri": ""
  },
  {
    "id": "96",
    "name": "Server 4",
    "size": "",
    "quality": "FM",
    "link_order": "4",
    "movie_id": "97",
    "url": "https://filemoon.in/e/rhk07ugsrxby",
    "type": "Embed",
    "status": "1",
    "skip_available": "0",
    "intro_start": "00:00:00",
    "intro_end": "0",
    "end_credits_marker": "0",
    "link_type": "0",
    "drm_uuid": "",
    "drm_license_uri": ""
  }
]