[
  {
    "id": "8510",
    "name": "PREMIUM SERVER",
    "size": "",
    "quality": "",
    "link_order": "-1",
    "movie_id": "2093",
    "url": "http://89.40.6.249:8080/1416/Virata+Parvam+%282022%29+UNCUT+720p+HDRip+%5BDual+Audio%5D+%5BHindi+or.mkv?hash=AgADzg",
    "type": "Mp4",
    "status": "1",
    "skip_available": "0",
    "intro_start": "",
    "intro_end": "",
    "end_credits_marker": "0",
    "link_type": "1",
    "drm_uuid": "",
    "drm_license_uri": ""
  },
  {
    "id": "8507",
    "name": "SERVER 1",
    "size": "",
    "quality": "",
    "link_order": "1",
    "movie_id": "2093",
    "url": "https://yomovies.cheap/virata-parvam-2022-hindi-dubbed-Watch-online-full-movie/",
    "type": "Streamhide",
    "status": "1",
    "skip_available": "0",
    "intro_start": "",
    "intro_end": "",
    "end_credits_marker": "0",
    "link_type": "0",
    "drm_uuid": "",
    "drm_license_uri": ""
  },
  {
    "id": "8508",
    "name": "SERVER 2",
    "size": "",
    "quality": "MULTI QUALITY ",
    "link_order": "2",
    "movie_id": "2093",
    "url": "https://oneupload.to/cii3z37idg0v",
    "type": "Streamhide",
    "status": "1",
    "skip_available": "0",
    "intro_start": "",
    "intro_end": "",
    "end_credits_marker": "0",
    "link_type": "0",
    "drm_uuid": "",
    "drm_license_uri": ""
  },
  {
    "id": "8509",
    "name": "SERVER 3",
    "size": "",
    "quality": "",
    "link_order": "3",
    "movie_id": "2093",
    "url": "http://89.40.6.249:8080/1416/Virata+Parvam+%282022%29+UNCUT+720p+HDRip+%5BDual+Audio%5D+%5BHindi+or.mkv?hash=AgADzg",
    "type": "Mp4",
    "status": "1",
    "skip_available": "0",
    "intro_start": "",
    "intro_end": "",
    "end_credits_marker": "0",
    "link_type": "0",
    "drm_uuid": "",
    "drm_license_uri": ""
  },
  {
    "id": "8511",
    "name": "SERVER 4",
    "size": "",
    "quality": "",
    "link_order": "4",
    "movie_id": "2093",
    "url": "https://dropload.io/aygks6pch32a",
    "type": "Streamhide",
    "status": "1",
    "skip_available": "0",
    "intro_start": "",
    "intro_end": "",
    "end_credits_marker": "0",
    "link_type": "0",
    "drm_uuid": "",
    "drm_license_uri": ""
  },
  {
    "id": "8512",
    "name": "SERVER 5",
    "size": "",
    "quality": "",
    "link_order": "5",
    "movie_id": "2093",
    "url": "https://filemoon.in/e/k4f9mzlwge8q",
    "type": "Embed",
    "status": "1",
    "skip_available": "0",
    "intro_start": "",
    "intro_end": "",
    "end_credits_marker": "0",
    "link_type": "0",
    "drm_uuid": "",
    "drm_license_uri": ""
  },
  {
    "id": "8513",
    "name": "SERVER 6",
    "size": "",
    "quality": "",
    "link_order": "6",
    "movie_id": "2093",
    "url": "https://embedwish.com/pgxrg0d9ikxb",
    "type": "Streamhide",
    "status": "1",
    "skip_available": "0",
    "intro_start": "",
    "intro_end": "",
    "end_credits_marker": "0",
    "link_type": "0",
    "drm_uuid": "",
    "drm_license_uri": ""
  }
]