[
  {
    "id": "9925",
    "name": "PREMIUM SERVER",
    "size": "",
    "quality": "",
    "link_order": "-1",
    "movie_id": "2213",
    "url": "https://n5.tg-drive.eu.org/e568b2502934a23dcd8ab3b6389227\t",
    "type": "Mp4",
    "status": "1",
    "skip_available": "0",
    "intro_start": "",
    "intro_end": "",
    "end_credits_marker": "0",
    "link_type": "1",
    "drm_uuid": "",
    "drm_license_uri": ""
  },
  {
    "id": "10172",
    "name": "AUTO SERVER",
    "size": "",
    "quality": "HINDI",
    "link_order": "0",
    "movie_id": "2213",
    "url": "https://embed.smashystream.com/playere.php?tmdb=984092",
    "type": "Embed",
    "status": "1",
    "skip_available": "0",
    "intro_start": "",
    "intro_end": "0",
    "end_credits_marker": "0",
    "link_type": "0",
    "drm_uuid": "",
    "drm_license_uri": ""
  },
  {
    "id": "10173",
    "name": "AUTO SERVER",
    "size": "",
    "quality": "HINDI",
    "link_order": "0",
    "movie_id": "2213",
    "url": "https://nxstreaming.site/GET-SERVERS/Embed.php?tmdb=984092",
    "type": "Embed",
    "status": "1",
    "skip_available": "0",
    "intro_start": "",
    "intro_end": "0",
    "end_credits_marker": "0",
    "link_type": "0",
    "drm_uuid": "",
    "drm_license_uri": ""
  },
  {
    "id": "10174",
    "name": "AUTO SERVER",
    "size": "",
    "quality": "HINDI",
    "link_order": "0",
    "movie_id": "2213",
    "url": "https://new.filepress.store/watch/movie/984092",
    "type": "Embed",
    "status": "1",
    "skip_available": "0",
    "intro_start": "",
    "intro_end": "",
    "end_credits_marker": "0",
    "link_type": "0",
    "drm_uuid": "",
    "drm_license_uri": ""
  },
  {
    "id": "9909",
    "name": "SERVER 1",
    "size": "",
    "quality": "",
    "link_order": "1",
    "movie_id": "2213",
    "url": "https://n5.tg-drive.eu.org/e568b2502934a23dcd8ab3b6389227",
    "type": "Mp4",
    "status": "1",
    "skip_available": "0",
    "intro_start": "",
    "intro_end": "0",
    "end_credits_marker": "0",
    "link_type": "0",
    "drm_uuid": "",
    "drm_license_uri": ""
  },
  {
    "id": "9911",
    "name": "SERVER 2",
    "size": "",
    "quality": "MULTI QUALITY",
    "link_order": "2",
    "movie_id": "2213",
    "url": "https://oneupload.to/0acu0991kfbp",
    "type": "Streamhide",
    "status": "1",
    "skip_available": "0",
    "intro_start": "",
    "intro_end": "",
    "end_credits_marker": "0",
    "link_type": "0",
    "drm_uuid": "",
    "drm_license_uri": ""
  },
  {
    "id": "9912",
    "name": "SERVER 3",
    "size": "",
    "quality": "",
    "link_order": "3",
    "movie_id": "2213",
    "url": "https://dropload.io/s1jwd6ww7j1k",
    "type": "Streamhide",
    "status": "1",
    "skip_available": "0",
    "intro_start": "",
    "intro_end": "",
    "end_credits_marker": "0",
    "link_type": "0",
    "drm_uuid": "",
    "drm_license_uri": ""
  },
  {
    "id": "9913",
    "name": "SERVER 4",
    "size": "",
    "quality": "",
    "link_order": "4",
    "movie_id": "2213",
    "url": "https://filemoon.in/e/jcr1y00bjatw/Gunpowder_Milkshake_2021_720p_BluRay_Hindi_English_ESubs_MoviesMod_org",
    "type": "Embed",
    "status": "1",
    "skip_available": "0",
    "intro_start": "",
    "intro_end": "",
    "end_credits_marker": "0",
    "link_type": "0",
    "drm_uuid": "",
    "drm_license_uri": ""
  },
  {
    "id": "9914",
    "name": "SERVER 5",
    "size": "",
    "quality": "",
    "link_order": "5",
    "movie_id": "2213",
    "url": "https://wishfast.top/r7s1ls8xy659",
    "type": "Streamhide",
    "status": "1",
    "skip_available": "0",
    "intro_start": "",
    "intro_end": "",
    "end_credits_marker": "0",
    "link_type": "0",
    "drm_uuid": "",
    "drm_license_uri": ""
  },
  {
    "id": "9915",
    "name": "SERVER 6",
    "size": "",
    "quality": "",
    "link_order": "6",
    "movie_id": "2213",
    "url": "https://filelions.online/f/3j7thavltjuu",
    "type": "Streamhide",
    "status": "1",
    "skip_available": "0",
    "intro_start": "",
    "intro_end": "",
    "end_credits_marker": "0",
    "link_type": "0",
    "drm_uuid": "",
    "drm_license_uri": ""
  }
]