[
  {
    "id": "3184",
    "name": "480P",
    "size": "",
    "quality": "",
    "link_order": "0",
    "movie_id": "1004",
    "url": "https://movieshub.movieshubxd02.workers.dev/0:/Movieshubmirrorold/Qala_%282022%29_Hindi_480p_WEB-DL_ESub_Nexmovies.xyz.mkv",
    "type": "Mkv",
    "status": "1",
    "skip_available": "0",
    "intro_start": "",
    "intro_end": "",
    "end_credits_marker": "0",
    "link_type": "0",
    "drm_uuid": null,
    "drm_license_uri": null
  },
  {
    "id": "3185",
    "name": "1080P",
    "size": "",
    "quality": "",
    "link_order": "0",
    "movie_id": "1004",
    "url": "https://movieshub.movieshubxd02.workers.dev/0:/Movieshubmirrorold/Qala_%282022%29_Hindi_1080p_WEB-DL_ESub_Nexmovies.xyz.mkv",
    "type": "Mkv",
    "status": "1",
    "skip_available": "0",
    "intro_start": "",
    "intro_end": "",
    "end_credits_marker": "0",
    "link_type": "0",
    "drm_uuid": null,
    "drm_license_uri": null
  },
  {
    "id": "3186",
    "name": "720P",
    "size": "",
    "quality": "",
    "link_order": "0",
    "movie_id": "1004",
    "url": "https://movieshub.movieshubxd02.workers.dev/0:/Movieshubmirrorold/Qala%20%282022%29%20Hindi%20720p%20WEB-DL%20ESub%20Nexmovies.xyz.mkv",
    "type": "Mkv",
    "status": "1",
    "skip_available": "0",
    "intro_start": "",
    "intro_end": "",
    "end_credits_marker": "0",
    "link_type": "0",
    "drm_uuid": null,
    "drm_license_uri": null
  },
  {
    "id": "3187",
    "name": "SERVER HQ",
    "size": "",
    "quality": "",
    "link_order": "0",
    "movie_id": "1004",
    "url": "https://streamsb.net/e/o86rsw0o50hd.html",
    "type": "StreamSB",
    "status": "1",
    "skip_available": "0",
    "intro_start": "",
    "intro_end": "",
    "end_credits_marker": "0",
    "link_type": "0",
    "drm_uuid": null,
    "drm_license_uri": null
  },
  {
    "id": "3188",
    "name": "SERVER HD",
    "size": "",
    "quality": "",
    "link_order": "0",
    "movie_id": "1004",
    "url": "https://dood.la/d/2r0pnew6q9rb",
    "type": "DoodStream",
    "status": "1",
    "skip_available": "0",
    "intro_start": "",
    "intro_end": "",
    "end_credits_marker": "0",
    "link_type": "0",
    "drm_uuid": null,
    "drm_license_uri": null
  }
]