[
  {
    "id": "4094",
    "name": "SERVER MOVIESHUB",
    "size": "",
    "quality": "",
    "link_order": "-2",
    "movie_id": "1233",
    "url": "https://assets-1.mypowerdisk.com/transcode_video/768a02ae0ae76ea402e9798235dbe0f3/dash/5bfedec4c27a40a7530f30ed55ffb810.mpd",
    "type": "Dash",
    "status": "1",
    "skip_available": "0",
    "intro_start": "00:00:00",
    "intro_end": "0",
    "end_credits_marker": "0",
    "link_type": "0",
    "drm_uuid": null,
    "drm_license_uri": null
  },
  {
    "id": "4095",
    "name": "SERVER 1",
    "size": "",
    "quality": "",
    "link_order": "-1",
    "movie_id": "1233",
    "url": "https://movieshub.movieshubxd02.workers.dev/0:/Movieshubmirrorold/SIUTKSKMHD%20%282023%29%20Www.Movieshubapk.online.Bio%20720p%20HEVC%20HDRip%20Dual%20Audio%20x265%20ESubs.mkv",
    "type": "Mp4",
    "status": "1",
    "skip_available": "0",
    "intro_start": "",
    "intro_end": "0",
    "end_credits_marker": "0",
    "link_type": "0",
    "drm_uuid": null,
    "drm_license_uri": null
  },
  {
    "id": "4096",
    "name": "SERVER 2",
    "size": "",
    "quality": "",
    "link_order": "0",
    "movie_id": "1233",
    "url": "https://streamsb.net/e/qvwr4arrbwq8.html",
    "type": "StreamSB",
    "status": "1",
    "skip_available": "0",
    "intro_start": "",
    "intro_end": "",
    "end_credits_marker": "0",
    "link_type": "0",
    "drm_uuid": null,
    "drm_license_uri": null
  },
  {
    "id": "4097",
    "name": "SERVER 3",
    "size": "",
    "quality": "",
    "link_order": "0",
    "movie_id": "1233",
    "url": "https://dood.la/d/w0s3fztdv5at",
    "type": "DoodStream",
    "status": "1",
    "skip_available": "0",
    "intro_start": "",
    "intro_end": "",
    "end_credits_marker": "0",
    "link_type": "0",
    "drm_uuid": null,
    "drm_license_uri": null
  },
  {
    "id": "4098",
    "name": "SERVER 4",
    "size": "",
    "quality": "",
    "link_order": "0",
    "movie_id": "1233",
    "url": "https://voe.sx/mm0ox2uxp9e7",
    "type": "Voesx",
    "status": "1",
    "skip_available": "0",
    "intro_start": "",
    "intro_end": "",
    "end_credits_marker": "0",
    "link_type": "0",
    "drm_uuid": null,
    "drm_license_uri": null
  }
]