[
  {
    "id": "4639",
    "name": "SERVER MOVIESHUB",
    "size": "",
    "quality": "",
    "link_order": "0",
    "movie_id": "1362",
    "url": "https://assets-1.mypowerdisk.com/transcode_video/b0e857d2753c0e06ff16034895320b1f/dash/81d1fa1f5d43bd412c0f5f85a846e57f.mpd",
    "type": "Dash",
    "status": "1",
    "skip_available": "0",
    "intro_start": "",
    "intro_end": "",
    "end_credits_marker": "0",
    "link_type": "0",
    "drm_uuid": null,
    "drm_license_uri": null
  },
  {
    "id": "4640",
    "name": "SERVER 1",
    "size": "",
    "quality": "",
    "link_order": "0",
    "movie_id": "1362",
    "url": "https://movieshub.movieshub1.workers.dev/0:/Movieshubmirrornew/Dragon%20Dynasty%202006%20720p%20Hindi%20Movieshubapk.online.com.mkv",
    "type": "Mkv",
    "status": "1",
    "skip_available": "0",
    "intro_start": "",
    "intro_end": "",
    "end_credits_marker": "0",
    "link_type": "0",
    "drm_uuid": null,
    "drm_license_uri": null
  },
  {
    "id": "4641",
    "name": "SERVER 2",
    "size": "",
    "quality": "",
    "link_order": "0",
    "movie_id": "1362",
    "url": "https://streamsb.net/e/ehonusinzc4m.html",
    "type": "StreamSB",
    "status": "1",
    "skip_available": "0",
    "intro_start": "",
    "intro_end": "",
    "end_credits_marker": "0",
    "link_type": "0",
    "drm_uuid": null,
    "drm_license_uri": null
  },
  {
    "id": "4642",
    "name": "SERVER 3",
    "size": "",
    "quality": "",
    "link_order": "0",
    "movie_id": "1362",
    "url": " https://cdn.cloudkp.com/watch/GY4TQNBQ",
    "type": "Mp4",
    "status": "1",
    "skip_available": "0",
    "intro_start": "",
    "intro_end": "",
    "end_credits_marker": "0",
    "link_type": "0",
    "drm_uuid": null,
    "drm_license_uri": null
  },
  {
    "id": "4643",
    "name": "SERVER 4",
    "size": "",
    "quality": "",
    "link_order": "0",
    "movie_id": "1362",
    "url": "https://archive.dltelegram.workers.dev/394816",
    "type": "Mp4",
    "status": "1",
    "skip_available": "0",
    "intro_start": "",
    "intro_end": "",
    "end_credits_marker": "0",
    "link_type": "0",
    "drm_uuid": null,
    "drm_license_uri": null
  }
]