[
  {
    "id": "7112",
    "name": "PREMIUM SERVER",
    "size": "",
    "quality": "",
    "link_order": "-1",
    "movie_id": "1931",
    "url": "http://89.40.6.249:8080/203/The_Out_Laws_2023_720p_HEVC_NF_HDRip_ORG_Dual_2CH_x265_MSub_Movieshubapk.mkv?hash=AgADzw",
    "type": "Mp4",
    "status": "1",
    "skip_available": "0",
    "intro_start": "",
    "intro_end": "",
    "end_credits_marker": "0",
    "link_type": "1",
    "drm_uuid": "",
    "drm_license_uri": ""
  },
  {
    "id": "7107",
    "name": "SERVER 1",
    "size": "",
    "quality": "",
    "link_order": "0",
    "movie_id": "1931",
    "url": "https://movieshub.movieshub1.workers.dev/0:/Movieshubmirrornew/The.Out-Laws.2023.720p.HEVC.NF.HDRip.ORG.Dual.2CH.x265.MSub%20%5BMovieshubapk.online%5D.mkv",
    "type": "Mp4",
    "status": "1",
    "skip_available": "0",
    "intro_start": "",
    "intro_end": "",
    "end_credits_marker": "0",
    "link_type": "0",
    "drm_uuid": "",
    "drm_license_uri": ""
  },
  {
    "id": "7108",
    "name": "SERVER 2",
    "size": "SB",
    "quality": "720P",
    "link_order": "0",
    "movie_id": "1931",
    "url": "https://streamsb.net/e/bk9jjne4tpse.html",
    "type": "StreamSB",
    "status": "1",
    "skip_available": "0",
    "intro_start": "",
    "intro_end": "0",
    "end_credits_marker": "0",
    "link_type": "0",
    "drm_uuid": "",
    "drm_license_uri": ""
  },
  {
    "id": "7109",
    "name": "SERVER 3",
    "size": "SH",
    "quality": "720P",
    "link_order": "0",
    "movie_id": "1931",
    "url": "https://ahvsh.com/e/26dk94qqmey9",
    "type": "Embed",
    "status": "1",
    "skip_available": "0",
    "intro_start": "",
    "intro_end": "0",
    "end_credits_marker": "0",
    "link_type": "0",
    "drm_uuid": "",
    "drm_license_uri": ""
  },
  {
    "id": "7110",
    "name": "SERVER 4",
    "size": "SW",
    "quality": "720P",
    "link_order": "0",
    "movie_id": "1931",
    "url": "https://embedwish.com/o566tg2esmq8",
    "type": "Streamhide",
    "status": "1",
    "skip_available": "0",
    "intro_start": "",
    "intro_end": "",
    "end_credits_marker": "0",
    "link_type": "0",
    "drm_uuid": "",
    "drm_license_uri": ""
  },
  {
    "id": "7111",
    "name": "SERVER 5",
    "size": "GLOBAL SERVER",
    "quality": "720P",
    "link_order": "0",
    "movie_id": "1931",
    "url": "https://embedwish.com/e/o566tg2esmq8",
    "type": "Embed",
    "status": "1",
    "skip_available": "0",
    "intro_start": "",
    "intro_end": "0",
    "end_credits_marker": "0",
    "link_type": "0",
    "drm_uuid": "",
    "drm_license_uri": ""
  }
]